[{"job": "Android Framework", "company": "南京易测", "salary": "15-20K", "link": "https://www.zhipin.com/job_detail/9a03369835cd223b0Xxy2tu9GFM~.html"}, {"job": "Android framework工程师", "company": "掌阅科技", "salary": "30-35K·13薪", "link": "https://www.zhipin.com/job_detail/6febb034cb8036690nN_0924GFI~.html"}, {"job": "Android framework工程师", "company": "感臻科技", "salary": "12-24K", "link": "https://www.zhipin.com/job_detail/cda071f47d4151350HR-0tu0EVI~.html"}, {"job": "Android framework工程师", "company": "远特科技", "salary": "13-20K", "link": "https://www.zhipin.com/job_detail/9b9d4549f7b3ccf71H163N29FFU~.html"}, {"job": "Android 安卓", "company": "软通动力", "salary": "15-28K", "link": "https://www.zhipin.com/job_detail/022fbd23313d76ef1Xx-3tW9FlQ~.html"}, {"job": "Android Framework工程师-深圳", "company": "软通动力", "salary": "15-30K", "link": "https://www.zhipin.com/job_detail/4222b42f0d9f43f70X1929W8F1Q~.html"}, {"job": "android  framework开发工程师", "company": "巴夫洛生态农业科技", "salary": "15-30K·15薪", "link": "https://www.zhipin.com/job_detail/dc8f275bfeaa39610X183Nq6EVQ~.html"}, {"job": "Android FrameWork开发工程师", "company": "星砺达", "salary": "14-25K", "link": "https://www.zhipin.com/job_detail/9af7d527f6ffe7230Xxz09u0FFA~.html"}, {"job": "安卓android", "company": "德科信息", "salary": "12-22K·13薪", "link": "https://www.zhipin.com/job_detail/3e711e82fc95345b03d-2N-9F1Q~.html"}, {"job": "android framework框架工程师", "company": "芯知软件", "salary": "20-35K", "link": "https://www.zhipin.com/job_detail/602b30fc5fd8a81903R92t-1FVs~.html"}, {"job": "Android安卓开发", "company": "软通动力", "salary": "12-24K", "link": "https://www.zhipin.com/job_detail/17992abce0d7f3610Xx42tu5GFQ~.html"}, {"job": "android  framework开发工程师", "company": "深圳市前海和诚信息", "salary": "18-35K", "link": "https://www.zhipin.com/job_detail/03135808fa591f250X193tm8Flo~.html"}, {"job": "android framework框架工程师", "company": "芯知软件", "salary": "15-25K", "link": "https://www.zhipin.com/job_detail/707b5e6303fae4f00HR53Nu5FFE~.html"}, {"job": "Android安卓工程师", "company": "联合医务", "salary": "12-24K·13薪", "link": "https://www.zhipin.com/job_detail/102d07135443fcd60Xx529m9GFs~.html"}, {"job": "Android framework软件研发工程师", "company": "德赛西威", "salary": "13-25K·13薪", "link": "https://www.zhipin.com/job_detail/b27505f3a1750db50XZ53t--F1c~.html"}, {"job": "安卓android", "company": "信力融创", "salary": "10-15K", "link": "https://www.zhipin.com/job_detail/7ea545980d26a5070XZ40tu6FVc~.html"}, {"job": "Android安卓工程师", "company": "拉科菲希科技", "salary": "20-30K", "link": "https://www.zhipin.com/job_detail/5ff1002be9dc4f250nJz3tu4GFE~.html"}, {"job": "Android/IOS", "company": "中软国际科技", "salary": "11-20K", "link": "https://www.zhipin.com/job_detail/c9c14b1c61049c3a1H140921FlY~.html"}, {"job": "Android 相机HAL/Framework工程师", "company": "上海传英", "salary": "10-20K", "link": "https://www.zhipin.com/job_detail/59d3f277dbf3b80a0nR_2969EVs~.html"}, {"job": "安卓 framework", "company": "紫旗", "salary": "10-13K", "link": "https://www.zhipin.com/job_detail/6ecebee9149b67011XJ50t68FVI~.html"}, {"job": "android安卓工程师", "company": "丰远国际", "salary": "15-30K", "link": "https://www.zhipin.com/job_detail/be1b818dc619b9141X1z3du5E1A~.html"}, {"job": "Android安卓工程师", "company": "匠鑫", "salary": "10-20K", "link": "https://www.zhipin.com/job_detail/a0e2c57a31aa64a91XR82t2_GVQ~.html"}, {"job": "Android安卓开发工程师", "company": "编程猫", "salary": "15-30K", "link": "https://www.zhipin.com/job_detail/ff9d22c3e0d1faba0nRy39m5GVQ~.html"}, {"job": "Android安卓底层工程师", "company": "轻程", "salary": "15-25K", "link": "https://www.zhipin.com/job_detail/9ca03f1419325c510X1539-0GVo~.html"}, {"job": "Android", "company": "广东欧珀", "salary": "15-30K", "link": "https://www.zhipin.com/job_detail/c66959ae6533963c03x-39q9GFs~.html"}, {"job": "高级Android安卓工程师", "company": "拉科菲希科技", "salary": "22-35K", "link": "https://www.zhipin.com/job_detail/762859d63ec8c1c00nJz3tu-FVs~.html"}, {"job": "Android", "company": "腾讯", "salary": "25-45K", "link": "https://www.zhipin.com/job_detail/00fbaa893627f2011X1909W9EVA~.html"}, {"job": "Android", "company": "OPPO", "salary": "15-30K", "link": "https://www.zhipin.com/job_detail/f8c6183e33e12cd30XV50t6_EVI~.html"}, {"job": "Android", "company": "OPPO", "salary": "15-30K", "link": "https://www.zhipin.com/job_detail/12de2322527f29551XV609u5F1U~.html"}, {"job": "Android", "company": "OPPO", "salary": "15-30K", "link": "https://www.zhipin.com/job_detail/4ad8054917a112141XV-3tW6FVQ~.html"}, {"job": "Android", "company": "vivo", "salary": "21-30K", "link": "https://www.zhipin.com/job_detail/229de788afc5fb7b1H1_3tm7EFs~.html"}, {"job": "Android", "company": "vivo", "salary": "20-40K", "link": "https://www.zhipin.com/job_detail/936c526f915d92881XJ93tu_GVY~.html"}, {"job": "Android", "company": "OPPO", "salary": "20-40K", "link": "https://www.zhipin.com/job_detail/8b46df68204cbb341XV-39q8ElY~.html"}, {"job": "Android 安卓高级开发", "company": "北京行景科技", "salary": "35-40K", "link": "https://www.zhipin.com/job_detail/a28fd31ac3502c900XN409S6GVI~.html"}, {"job": "Android", "company": "OPPO", "salary": "15-30K", "link": "https://www.zhipin.com/job_detail/d2aa02afe126cf981XV63t-1EFU~.html"}, {"job": "Android", "company": "OPPO", "salary": "15-30K", "link": "https://www.zhipin.com/job_detail/c84901e3db6f6add1XZ63N21F1A~.html"}, {"job": "Android", "company": "OPPO", "salary": "15-30K", "link": "https://www.zhipin.com/job_detail/c291f8acd481386b1XV70tm5FVE~.html"}, {"job": "Android", "company": "OPPO", "salary": "20-25K", "link": "https://www.zhipin.com/job_detail/9e704b55fe261df81XV-0tu8GFc~.html"}, {"job": "Android", "company": "广东欧珀", "salary": "20-40K", "link": "https://www.zhipin.com/job_detail/f7c96963fb606c570XZz29m4EVA~.html"}, {"job": "Android", "company": "腾讯", "salary": "21-40K·18薪", "link": "https://www.zhipin.com/job_detail/33b5804c3e9c2fa703Fz39i0FlM~.html"}, {"job": "Android", "company": "软通动力", "salary": "15-30K", "link": "https://www.zhipin.com/job_detail/630e73649557e4a80HR70tm0EFU~.html"}, {"job": "Android", "company": "OPPO", "salary": "15-30K", "link": "https://www.zhipin.com/job_detail/be0b43c3407f9f071XN93du1F1c~.html"}, {"job": "Android", "company": "有赞", "salary": "20-30K", "link": "https://www.zhipin.com/job_detail/2a274e636eb502231n1y3Nq5EFM~.html"}, {"job": "Android", "company": "广东欧珀", "salary": "20-40K", "link": "https://www.zhipin.com/job_detail/c4a5b9df65e518dc0XZz29m6FFU~.html"}, {"job": "Android", "company": "OPPO", "salary": "15-30K", "link": "https://www.zhipin.com/job_detail/1dc26b1ac534ae0e1HJ539m0EVA~.html"}, {"job": "Android", "company": "OPPO广东移动...", "salary": "20-25K", "link": "https://www.zhipin.com/job_detail/43c67843f431751c0XR439q0ElY~.html"}, {"job": "Android", "company": "广东欧珀", "salary": "20-30K", "link": "https://www.zhipin.com/job_detail/e83fe903b9a0bebc0nR73N25FlA~.html"}, {"job": "Android", "company": "CloudBU", "salary": "15-30K·15薪", "link": "https://www.zhipin.com/job_detail/0b005b823d7347970XN53d60EFo~.html"}, {"job": "Android", "company": "有方科技", "salary": "15-25K", "link": "https://www.zhipin.com/job_detail/b073cca7aed7ed431XV72tm7EFQ~.html"}, {"job": "Android/安卓工程师", "company": "壹捌无限公司", "salary": "12-16K", "link": "https://www.zhipin.com/job_detail/d79fc7967a3174f703d80ti8GVo~.html"}, {"job": "Android", "company": "OPPO", "salary": "15-30K", "link": "https://www.zhipin.com/job_detail/e3fcb4d1e68629c31XV429i0EVs~.html"}, {"job": "Android", "company": "云中飞", "salary": "15-30K·13薪", "link": "https://www.zhipin.com/job_detail/7277085301fd766c0nxy3d60E1M~.html"}, {"job": "安卓Framework 开发", "company": "国文科技", "salary": "15-30K", "link": "https://www.zhipin.com/job_detail/75afe594816be7d20XF539q9EVU~.html"}, {"job": "Android", "company": "腾讯", "salary": "25-45K·17薪", "link": "https://www.zhipin.com/job_detail/dca55d86fe657fa303d629S9EVY~.html"}, {"job": "Android", "company": "OPPO", "salary": "20-35K", "link": "https://www.zhipin.com/job_detail/e0eb00fa2f9c69631HN82dW9EVI~.html"}, {"job": "Android", "company": "OPPO", "salary": "15-30K", "link": "https://www.zhipin.com/job_detail/cf04e81cec68ecd71XV70t28F1o~.html"}, {"job": "Android", "company": "OPPO", "salary": "15-30K", "link": "https://www.zhipin.com/job_detail/d303f984abf1cf0d1XV70t25FFA~.html"}, {"job": "Android", "company": "OPPO", "salary": "15-30K", "link": "https://www.zhipin.com/job_detail/2b3f13d9a9e4728c1XV70t21GVM~.html"}, {"job": "Android", "company": "OPPO", "salary": "15-30K", "link": "https://www.zhipin.com/job_detail/a981c9da9a7fd2651XV42tW7FlI~.html"}, {"job": "Android", "company": "广东欧珀", "salary": "20-40K·15薪", "link": "https://www.zhipin.com/job_detail/a22b5d4fbb66841e03N53d24GFA~.html"}, {"job": "Android framework 系统工程师", "company": "智英实业", "salary": "12-18K", "link": "https://www.zhipin.com/job_detail/332010e9bd603bbc0nBy39W9Elc~.html"}, {"job": "Android", "company": "腾讯互娱", "salary": "15-30K", "link": "https://www.zhipin.com/job_detail/60730f2031e3f85b0nx_3t61FVc~.html"}, {"job": "Android", "company": "OPPO", "salary": "15-30K", "link": "https://www.zhipin.com/job_detail/7c47ad795bd0ec3d1XV40t28EVY~.html"}, {"job": "Android", "company": "OPPO", "salary": "20-40K", "link": "https://www.zhipin.com/job_detail/973e4513b050ddc81XV73Nq7F1s~.html"}, {"job": "Android", "company": "OPPO", "salary": "15-30K", "link": "https://www.zhipin.com/job_detail/7bc937120999b5d71XV429i4Elc~.html"}, {"job": "Android", "company": "vivo", "salary": "30-60K", "link": "https://www.zhipin.com/job_detail/c395aac6c12225881Hx-2t21EFc~.html"}, {"job": "android", "company": "阿里巴巴国际事业部", "salary": "25-35K·16薪", "link": "https://www.zhipin.com/job_detail/827761086d569fe203Z809q6EFM~.html"}, {"job": "Android", "company": "vivo", "salary": "15-30K", "link": "https://www.zhipin.com/job_detail/1b4484dd44696e7f0Xx439u_EVM~.html"}, {"job": "Android", "company": "百度", "salary": "15-30K", "link": "https://www.zhipin.com/job_detail/ebbedab8ec9f548c1Xx93Ny8EVI~.html"}, {"job": "Android", "company": "华一集团", "salary": "12-15K", "link": "https://www.zhipin.com/job_detail/7b72729a22e6bfdb0XV72dq9E1s~.html"}, {"job": "Android", "company": "OPPO", "salary": "15-30K", "link": "https://www.zhipin.com/job_detail/f42548c02e01a5eb1H1-29y4GVs~.html"}, {"job": "Android", "company": "法本", "salary": "13-18K", "link": "https://www.zhipin.com/job_detail/3e49c3b2e173bca50HR-292_GFM~.html"}, {"job": "Android", "company": "广东欧珀", "salary": "15-30K", "link": "https://www.zhipin.com/job_detail/270b127d3196220e0XN93Nq-FlM~.html"}, {"job": "Android", "company": "腾讯", "salary": "15-30K", "link": "https://www.zhipin.com/job_detail/30e117f5f1beef790Xx-29i7GVU~.html"}, {"job": "安卓framework工程师", "company": "创盈芯", "salary": "13-20K", "link": "https://www.zhipin.com/job_detail/804d5f51ecfcc96a0XJz09-0Elc~.html"}, {"job": "Android", "company": "OPPO", "salary": "11-20K", "link": "https://www.zhipin.com/job_detail/9d2b7c41b296207903F_3dq9FlA~.html"}, {"job": "Android", "company": "腾讯", "salary": "20-40K", "link": "https://www.zhipin.com/job_detail/db1e94a85e5736740XJ62NW4GFs~.html"}, {"job": "Android", "company": "OPPO", "salary": "15-30K", "link": "https://www.zhipin.com/job_detail/f01c6d48484245101HB63d24E1E~.html"}, {"job": "Android", "company": "浩科", "salary": "15-16K", "link": "https://www.zhipin.com/job_detail/d67b0260b323c7841XR52d69ElI~.html"}, {"job": "APP 工程师  Android  IOS", "company": "宜诺科技", "salary": "16-26K", "link": "https://www.zhipin.com/job_detail/8e24b1c3024c82c403B429i4EFY~.html"}, {"job": "Android", "company": "OPPO", "salary": "15-30K", "link": "https://www.zhipin.com/job_detail/5991d09693a117cc1X1-2Ny_ElQ~.html"}, {"job": "Android", "company": "OPPO", "salary": "15-30K", "link": "https://www.zhipin.com/job_detail/2d1c5350c39f7d2a1HB42t61GVE~.html"}, {"job": "安卓Android高级研发工程师", "company": "百度", "salary": "15-30K", "link": "https://www.zhipin.com/job_detail/52fb2c6d6b8ea2bc0nJ63tS5F1E~.html"}, {"job": "Android", "company": "招商金科", "salary": "20-21K", "link": "https://www.zhipin.com/job_detail/044646bef1982a6d1Hx62d-0FVo~.html"}, {"job": "Android", "company": "OPPO", "salary": "25-40K", "link": "https://www.zhipin.com/job_detail/c240b4db1e3fcac71HV-3dS0EVc~.html"}, {"job": "Android", "company": "阿里巴巴集团", "salary": "25-45K·16薪", "link": "https://www.zhipin.com/job_detail/6227a0e3753dd30e1XB539i-Elc~.html"}, {"job": "Android", "company": "OPPO", "salary": "15-30K", "link": "https://www.zhipin.com/job_detail/5eb02d91e85590e41XV40t29GFM~.html"}, {"job": "Android", "company": "腾讯", "salary": "30-55K", "link": "https://www.zhipin.com/job_detail/cc80ff9f06c3b58b03Fz2Nu7FVA~.html"}, {"job": "Android安卓开发工程师", "company": "奇点创艺", "salary": "10-15K", "link": "https://www.zhipin.com/job_detail/f8bd3ce978d0c5df1HRy39y1FVA~.html"}, {"job": "Android", "company": "OPPO", "salary": "15-30K", "link": "https://www.zhipin.com/job_detail/26320407520073191XV73NS4F1o~.html"}, {"job": "Android", "company": "OPPO", "salary": "20-40K", "link": "https://www.zhipin.com/job_detail/0e12475d0ec4abb31HJ-2d2-GFM~.html"}, {"job": "Android", "company": "阿里巴巴集团", "salary": "25-50K·13薪", "link": "https://www.zhipin.com/job_detail/7d47aede4ab612030Xd92d65EFc~.html"}, {"job": "Android", "company": "OPPO", "salary": "15-30K", "link": "https://www.zhipin.com/job_detail/bdc3563e092397571XV70ti9EFA~.html"}, {"job": "Android", "company": "百度", "salary": "15-30K", "link": "https://www.zhipin.com/job_detail/65e41e1b3d6d79ee0nFz3dy0GFI~.html"}, {"job": "Android", "company": "菜鸟网络", "salary": "20-35K", "link": "https://www.zhipin.com/job_detail/3e37ed1c8a39bfa41XZ53921GFY~.html"}, {"job": "Android", "company": "OPPO", "salary": "18-30K", "link": "https://www.zhipin.com/job_detail/02be73a007cb56ed1XV439m4F1A~.html"}, {"job": "Android", "company": "阿里集团", "salary": "20-40K", "link": "https://www.zhipin.com/job_detail/922928895da926b10HR_29W7ElE~.html"}, {"job": "Android", "company": "OPPO", "salary": "15-30K", "link": "https://www.zhipin.com/job_detail/d9b151efb4266e861XV70tm1GFo~.html"}, {"job": "Android", "company": "广东欧珀", "salary": "20-40K", "link": "https://www.zhipin.com/job_detail/66d33fb9282540400XJ_09u4F1Q~.html"}, {"job": "Android", "company": "广东欧珀", "salary": "15-30K", "link": "https://www.zhipin.com/job_detail/8d99da4c19f38b5803B62ty-F1c~.html"}, {"job": "Android", "company": "广东欧珀", "salary": "20-40K·16薪", "link": "https://www.zhipin.com/job_detail/0ad63d2d7bfacdda0XVy3du4FVM~.html"}, {"job": "Android", "company": "广东欧珀", "salary": "25-40K", "link": "https://www.zhipin.com/job_detail/7fd220b653c6441d0XN42dm1EVA~.html"}, {"job": "Android", "company": "金森数码", "salary": "10-15K", "link": "https://www.zhipin.com/job_detail/b0b143f971ca9c141nx52d-6EVo~.html"}, {"job": "Android", "company": "欧珀(OPPO)", "salary": "12-21K", "link": "https://www.zhipin.com/job_detail/6d50a5527d54080e03Z509S8FFs~.html"}, {"job": "Android", "company": "广东欧珀", "salary": "20-40K", "link": "https://www.zhipin.com/job_detail/e28978a1cf1e534c0XN62di7FFU~.html"}, {"job": "Android", "company": "软通动力", "salary": "11-18K", "link": "https://www.zhipin.com/job_detail/e4ea7144992eb0ec1XF-3ti-GVs~.html"}, {"job": "Android", "company": "OPPO", "salary": "15-30K", "link": "https://www.zhipin.com/job_detail/4d06c9e04a529a011XV53tW7EVE~.html"}, {"job": "Android", "company": "法本", "salary": "17-20K", "link": "https://www.zhipin.com/job_detail/9f40c13c6aab02420HR93dW4GVI~.html"}, {"job": "Android", "company": "绿联科技", "salary": "16-30K", "link": "https://www.zhipin.com/job_detail/d1414eb93242ced303x82N64GVI~.html"}, {"job": "Android", "company": "vivo", "salary": "25-35K", "link": "https://www.zhipin.com/job_detail/d02f3216d39f0a821HJ82Nu1E1o~.html"}, {"job": "Android", "company": "OPPO", "salary": "20-40K", "link": "https://www.zhipin.com/job_detail/0afc4c2df67441781HB539m0FlM~.html"}, {"job": "Android", "company": "OPPO广东移动...", "salary": "13-26K", "link": "https://www.zhipin.com/job_detail/d1fe5406ecb87c9903xz09i5GVA~.html"}, {"job": "Android", "company": "腾讯", "salary": "25-50K", "link": "https://www.zhipin.com/job_detail/a201612768ff7c331nVz39S-.html"}, {"job": "Android", "company": "OPPO", "salary": "30-50K", "link": "https://www.zhipin.com/job_detail/bbd59a466e577d270X170tq1EVM~.html"}, {"job": "Android", "company": "OPPO", "salary": "20-40K", "link": "https://www.zhipin.com/job_detail/8d58edb960240bee1HVz2d60FlY~.html"}, {"job": "Android", "company": "OPPO", "salary": "20-35K", "link": "https://www.zhipin.com/job_detail/1a8f56a17f8cb9441Xd839y-FlM~.html"}, {"job": "Android", "company": "华为", "salary": "15-30K", "link": "https://www.zhipin.com/job_detail/d92687ec7514758e0Xx92tm7Flc~.html"}, {"job": "Android安卓开发工程师", "company": "富微科创", "salary": "9-13K", "link": "https://www.zhipin.com/job_detail/25281a634e4b86080XB92N29Fls~.html"}, {"job": "Android", "company": "广东欧珀", "salary": "12-20K", "link": "https://www.zhipin.com/job_detail/3bdee0613601e19d0XVy3dq7E1I~.html"}, {"job": "Android", "company": "广东欧珀", "salary": "15-30K", "link": "https://www.zhipin.com/job_detail/871c84d5353735520XB42N-8FVI~.html"}, {"job": "Android", "company": "OPPO", "salary": "15-30K", "link": "https://www.zhipin.com/job_detail/7ca49dd115a2707c1XV73dq-F1E~.html"}, {"job": "Android", "company": "OPPO广东移动...", "salary": "15-30K", "link": "https://www.zhipin.com/job_detail/88df9e6701940e231XF62Ny_FFU~.html"}, {"job": "Android", "company": "阿里巴巴集团", "salary": "25-35K", "link": "https://www.zhipin.com/job_detail/1cf4cd093164c0fa1nx939u6F1s~.html"}, {"job": "Android", "company": "vivo", "salary": "20-40K", "link": "https://www.zhipin.com/job_detail/36f662b1377207dc1HF83ty7FVU~.html"}, {"job": "Android", "company": "OPPO", "salary": "20-30K", "link": "https://www.zhipin.com/job_detail/f9782e3e3904c87b1Xd93Ny9F1E~.html"}, {"job": "Android", "company": "广东欧珀", "salary": "25-45K", "link": "https://www.zhipin.com/job_detail/5b2bd80a4775f73a0XB_2NS6FVY~.html"}, {"job": "Android", "company": "OPPO", "salary": "15-30K", "link": "https://www.zhipin.com/job_detail/37143961c735c69b1HVz2ty_FFY~.html"}, {"job": "Android", "company": "OPPO", "salary": "20-40K", "link": "https://www.zhipin.com/job_detail/7e6486b183b7ffec1n1-2Nu0FlA~.html"}, {"job": "android安卓开发工程师", "company": "有源诚", "salary": "10-15K", "link": "https://www.zhipin.com/job_detail/0d8b9947f8aac0dc1HB509m8FFE~.html"}, {"job": "Android", "company": "百度", "salary": "18-35K", "link": "https://www.zhipin.com/job_detail/21e8929c1b258a0e1nBz3N-6Els~.html"}, {"job": "Android", "company": "OPPO", "salary": "20-35K", "link": "https://www.zhipin.com/job_detail/983d1305f497c7111HF63dS4EVQ~.html"}, {"job": "Android", "company": "百度", "salary": "15-30K", "link": "https://www.zhipin.com/job_detail/ccb7481ddc5ed1900XRz09m8FVU~.html"}, {"job": "Android", "company": "腾讯", "salary": "20-30K", "link": "https://www.zhipin.com/job_detail/e2d481743c042ba40nB83tq7F1c~.html"}, {"job": "Android", "company": "OPPO", "salary": "20-40K", "link": "https://www.zhipin.com/job_detail/124a054045422ac31XV92d6_FFs~.html"}, {"job": "Android", "company": "腾讯", "salary": "36-72K", "link": "https://www.zhipin.com/job_detail/ed7f1a52345dfb491nN509W-EVA~.html"}, {"job": "Android", "company": "广东欧珀", "salary": "30-50K", "link": "https://www.zhipin.com/job_detail/0646b01420bfa2110HR42965FVU~.html"}, {"job": "Android", "company": "阿里巴巴集团", "salary": "20-40K", "link": "https://www.zhipin.com/job_detail/df837efd8b04312e0nB72Nq1FVQ~.html"}, {"job": "Android", "company": "广东欧珀", "salary": "20-40K", "link": "https://www.zhipin.com/job_detail/a137bdb6427231b81HJz0928GVU~.html"}, {"job": "Android", "company": "广东欧珀", "salary": "20-40K", "link": "https://www.zhipin.com/job_detail/f52a070c3503f5e01HN62d28E1U~.html"}, {"job": "Android", "company": "OPPO", "salary": "20-30K", "link": "https://www.zhipin.com/job_detail/2abf6962c971a9d41HZ-2N6-FlM~.html"}, {"job": "Android", "company": "OPPO", "salary": "15-30K", "link": "https://www.zhipin.com/job_detail/b67178affe5a9ac31nN839q9F1U~.html"}, {"job": "Android", "company": "OPPO", "salary": "15-30K", "link": "https://www.zhipin.com/job_detail/b6c3c36a30d6aec31HN82Nm9E1Q~.html"}, {"job": "Android", "company": "OPPO", "salary": "15-30K", "link": "https://www.zhipin.com/job_detail/150459d69dd8112b1nN609-7Elo~.html"}, {"job": "Android", "company": "OPPO", "salary": "15-30K", "link": "https://www.zhipin.com/job_detail/dc3053f61aef14fa1XV639W0EFI~.html"}, {"job": "Android", "company": "OPPO", "salary": "15-30K", "link": "https://www.zhipin.com/job_detail/2dc78619f1767eef1XV73di4E1Y~.html"}, {"job": "Android", "company": "OPPO", "salary": "20-40K", "link": "https://www.zhipin.com/job_detail/fdc65bfc016684e01HB70965EVY~.html"}, {"job": "Android", "company": "OPPO", "salary": "30-60K", "link": "https://www.zhipin.com/job_detail/68cbea7dc9b316541n1-3tS_EFs~.html"}, {"job": "Android", "company": "OPPO", "salary": "24-40K", "link": "https://www.zhipin.com/job_detail/5db74bcc6caed4a41H1_2dW5GFc~.html"}, {"job": "Android", "company": "OPPO", "salary": "18-30K", "link": "https://www.zhipin.com/job_detail/ce747bc6032e8a1b1HF_0tS8EFs~.html"}, {"job": "Android", "company": "OPPO", "salary": "15-30K", "link": "https://www.zhipin.com/job_detail/78d718cc802716f51XV72dq7EFE~.html"}, {"job": "Android", "company": "OPPO", "salary": "15-30K", "link": "https://www.zhipin.com/job_detail/ba6d34516e225dc11Xd82t-7EVM~.html"}, {"job": "Android", "company": "海信集团", "salary": "25-50K", "link": "https://www.zhipin.com/job_detail/4038eab647a0a0831HV93tS5FFU~.html"}, {"job": "Android", "company": "OPPO", "salary": "15-30K", "link": "https://www.zhipin.com/job_detail/a0b3cf3823ca098a1XV40t-_GFA~.html"}, {"job": "Android", "company": "OPPO", "salary": "15-30K", "link": "https://www.zhipin.com/job_detail/f46452b95daf54f81XV53tu9ElM~.html"}, {"job": "Android", "company": "OPPO", "salary": "25-40K", "link": "https://www.zhipin.com/job_detail/7b007ad00e6b72cd1HJz3Nm9ElU~.html"}, {"job": "Android", "company": "OPPO", "salary": "20-40K", "link": "https://www.zhipin.com/job_detail/09609e937201a0751HN62t66E1Y~.html"}, {"job": "Android", "company": "广东欧珀", "salary": "20-40K", "link": "https://www.zhipin.com/job_detail/6e33ebf5b2932be31HN62d-0F1Q~.html"}, {"job": "Android", "company": "OPPO", "salary": "25-50K", "link": "https://www.zhipin.com/job_detail/9d289c23692053761n162N--GVA~.html"}, {"job": "Android", "company": "OPPO", "salary": "15-30K", "link": "https://www.zhipin.com/job_detail/4bf34458a2a24dcb03V72t26ElY~.html"}, {"job": "Android", "company": "OPPO", "salary": "15-30K", "link": "https://www.zhipin.com/job_detail/58565f12204520471X1929W7FVU~.html"}, {"job": "Android", "company": "OPPO", "salary": "15-30K", "link": "https://www.zhipin.com/job_detail/4a03a21ae39324da1n1-2tS6FFA~.html"}, {"job": "Android", "company": "广东欧珀", "salary": "25-50K·16薪", "link": "https://www.zhipin.com/job_detail/6952bfee5855377a0XN629-4F1E~.html"}, {"job": "Android", "company": "广东欧珀", "salary": "20-40K·15薪", "link": "https://www.zhipin.com/job_detail/1fb173bdfd2991c00XN63t-0FVs~.html"}, {"job": "Android", "company": "中软国际", "salary": "13-26K", "link": "https://www.zhipin.com/job_detail/641db9e1425ce5901nB-29-8EVM~.html"}, {"job": "Android", "company": "广东欧珀", "salary": "25-40K", "link": "https://www.zhipin.com/job_detail/a2585546447b896b1HN62du9F1A~.html"}, {"job": "Android", "company": "广东欧珀", "salary": "20-40K", "link": "https://www.zhipin.com/job_detail/d0e8ef6a7a1bc2ee1HN62d69GFc~.html"}, {"job": "Android", "company": "OPPO广东移动...", "salary": "20-35K", "link": "https://www.zhipin.com/job_detail/f5bca30c930f33d81HV62dm5GVY~.html"}, {"job": "Android", "company": "百度", "salary": "20-35K", "link": "https://www.zhipin.com/job_detail/844453409b9a3bf81Xx93Nm4FlY~.html"}, {"job": "Android", "company": "百度", "salary": "20-30K", "link": "https://www.zhipin.com/job_detail/1d8661d6216de4f61n1609-7EVA~.html"}, {"job": "Android", "company": "OPPO", "salary": "20-35K", "link": "https://www.zhipin.com/job_detail/ae987b75a354dca31n1-2Nu1ElE~.html"}, {"job": "Android", "company": "广东欧珀", "salary": "18-35K", "link": "https://www.zhipin.com/job_detail/5e7545031fe411520X1-0tS9FFI~.html"}, {"job": "Android", "company": "广东欧珀", "salary": "25-40K", "link": "https://www.zhipin.com/job_detail/7ce4ae528eb424d01HJz3Nu8GFs~.html"}, {"job": "Android", "company": "OPPO", "salary": "15-30K", "link": "https://www.zhipin.com/job_detail/8c235114c47a9ceb1XV72dW9GFI~.html"}, {"job": "Android", "company": "OPPO", "salary": "15-30K", "link": "https://www.zhipin.com/job_detail/7c3e5286675805101XV73di4GVE~.html"}, {"job": "Android", "company": "平安科技", "salary": "18-25K", "link": "https://www.zhipin.com/job_detail/6373dd7056ed77fb1Xdz2N-4EVo~.html"}, {"job": "Android", "company": "OPPO", "salary": "15-30K", "link": "https://www.zhipin.com/job_detail/b4dd84664cc9d8e11XV72tm7F1Q~.html"}, {"job": "Android", "company": "OPPO", "salary": "25-35K", "link": "https://www.zhipin.com/job_detail/cef4ab8b7c27610b1XV73di9F1c~.html"}, {"job": "Android", "company": "OPPO", "salary": "15-30K", "link": "https://www.zhipin.com/job_detail/fd4e8c0eea99c2221Xd83t20Fls~.html"}, {"job": "Android", "company": "OPPO", "salary": "15-30K", "link": "https://www.zhipin.com/job_detail/1799d07de168ae2103Ry3tq7F1U~.html"}, {"job": "Android", "company": "百度", "salary": "15-30K·14薪", "link": "https://www.zhipin.com/job_detail/e8588faaccb3ee7003R93Nq5EVo~.html"}, {"job": "Android", "company": "OPPO", "salary": "15-30K", "link": "https://www.zhipin.com/job_detail/bd505518664e252d1XV73du0FFo~.html"}, {"job": "Android", "company": "OPPO", "salary": "15-30K", "link": "https://www.zhipin.com/job_detail/cf041b4184eec6371HF_2tm7EFA~.html"}, {"job": "Android", "company": "OPPO", "salary": "15-30K", "link": "https://www.zhipin.com/job_detail/3f4787ee2e9177351XV709m7GVA~.html"}, {"job": "android", "company": "法本", "salary": "12-18K", "link": "https://www.zhipin.com/job_detail/70889bd088cec8050HR_2NS7FFs~.html"}, {"job": "Android", "company": "百度", "salary": "25-40K", "link": "https://www.zhipin.com/job_detail/f81629372c1ebde00nZ63926GFU~.html"}, {"job": "Android", "company": "腾讯", "salary": "20-21K", "link": "https://www.zhipin.com/job_detail/9c24d35e6989f2510nN42dS7E1o~.html"}, {"job": "Android", "company": "OPPO", "salary": "25-45K", "link": "https://www.zhipin.com/job_detail/7f4c29bda9864d561XV629S1GFM~.html"}, {"job": "Android", "company": "OPPO", "salary": "20-40K", "link": "https://www.zhipin.com/job_detail/8509f02c09a7bbd51HF52Nq_E1U~.html"}, {"job": "Android", "company": "OPPO", "salary": "15-25K", "link": "https://www.zhipin.com/job_detail/f7cdccdadd1e34950nZ-2dy0F1A~.html"}, {"job": "Android", "company": "百度", "salary": "15-30K", "link": "https://www.zhipin.com/job_detail/5e80f7efe3637d370nV53ty1FlE~.html"}, {"job": "Android安卓开发工程师", "company": "飞蜂软件", "salary": "8-13K", "link": "https://www.zhipin.com/job_detail/25a5766ab29a82521HJ43di4FFQ~.html"}, {"job": "Android", "company": "腾讯", "salary": "20-21K", "link": "https://www.zhipin.com/job_detail/b22eb04fc77b13f70nN42N29F1U~.html"}, {"job": "Android安卓开发工程师", "company": "智能屋", "salary": "6-8K", "link": "https://www.zhipin.com/job_detail/d1c48068e752f1781n162N6_FFM~.html"}, {"job": "Android/安卓逆向工程师", "company": "郑州曲率", "salary": "20-30K", "link": "https://www.zhipin.com/job_detail/01dbd50825ba35370nx83dS_FFA~.html"}, {"job": "Android", "company": "华为", "salary": "14-28K", "link": "https://www.zhipin.com/job_detail/ec6257b6c95376060X140tm-EFI~.html"}, {"job": "Android", "company": "阿里巴巴集团", "salary": "20-40K", "link": "https://www.zhipin.com/job_detail/51176891526670801nN60tW-FlA~.html"}, {"job": "Android", "company": "OPPO", "salary": "20-21K", "link": "https://www.zhipin.com/job_detail/ad58360566ef6cda1HVz2t-5FFo~.html"}, {"job": "Android", "company": "睿时尚", "salary": "15-25K", "link": "https://www.zhipin.com/job_detail/c7b06f6135f4895c0XF_2Nu1EVs~.html"}, {"job": "Android", "company": "云中飞", "salary": "25-50K", "link": "https://www.zhipin.com/job_detail/0aa44c648547c4f51X152tu0FFs~.html"}, {"job": "Android", "company": "OPPO", "salary": "20-25K·15薪", "link": "https://www.zhipin.com/job_detail/1112fdbb69d3ae9c0XJ-3ty9Flo~.html"}, {"job": "Android", "company": "深圳市欢太科技有...", "salary": "30-50K", "link": "https://www.zhipin.com/job_detail/1ec8ed82e5f77ec90HR629S0E1s~.html"}, {"job": "Android", "company": "OPPO", "salary": "15-25K", "link": "https://www.zhipin.com/job_detail/5b76c3c22a12745d0nZ82t26E1I~.html"}, {"job": "Android", "company": "道通科技", "salary": "18-35K·16薪", "link": "https://www.zhipin.com/job_detail/c9b17dd043a33ff00HR80tW9Elc~.html"}, {"job": "Android", "company": "云中飞", "salary": "18-35K", "link": "https://www.zhipin.com/job_detail/b719996f6f3d785d1HB409W7E1c~.html"}, {"job": "Android", "company": "Shopee", "salary": "20-40K·15薪", "link": "https://www.zhipin.com/job_detail/7e2932d92a2717bc0XB_3tm7GFY~.html"}, {"job": "Android", "company": "迅雷网络", "salary": "15-30K", "link": "https://www.zhipin.com/job_detail/476895b137e4787f1HF409S9Els~.html"}, {"job": "android", "company": "软通动力", "salary": "10-15K", "link": "https://www.zhipin.com/job_detail/4e5e4f7c17a539ff0XV82Nm5FFQ~.html"}, {"job": "Android", "company": "开思时代", "salary": "18-30K·13薪", "link": "https://www.zhipin.com/job_detail/3dc875af91d88a4a0HR829S6GFo~.html"}, {"job": "Android", "company": "广东欧珀", "salary": "15-25K", "link": "https://www.zhipin.com/job_detail/8e0f299f320b6a861H152N-_GFA~.html"}, {"job": "Android", "company": "法本", "salary": "13-25K", "link": "https://www.zhipin.com/job_detail/bb32959035f4c0270XN529q6F1c~.html"}, {"job": "Android", "company": "Shopee", "salary": "20-40K", "link": "https://www.zhipin.com/job_detail/c8340277fd9302490nN83tS1F1s~.html"}, {"job": "Android", "company": "法本", "salary": "12-20K", "link": "https://www.zhipin.com/job_detail/4ce48cea0a0e8a5a0nN52N29EVU~.html"}, {"job": "Android", "company": "云中飞", "salary": "15-30K", "link": "https://www.zhipin.com/job_detail/371ecce3b447a3d41HN43920EFQ~.html"}, {"job": "Android", "company": "中科创达软件", "salary": "11-21K", "link": "https://www.zhipin.com/job_detail/c6b2810607dbaaa60X162964FlY~.html"}, {"job": "Android", "company": "酷派集团", "salary": "20-25K", "link": "https://www.zhipin.com/job_detail/57e19c47b4e16f660HR-39q5E1o~.html"}, {"job": "android技术专家", "company": "跨越速运", "salary": "50-80K·15薪", "link": "https://www.zhipin.com/job_detail/6cd6086be59603260X143tq0FlM~.html"}, {"job": "Android", "company": "货拉拉科技", "salary": "18-35K", "link": "https://www.zhipin.com/job_detail/2151d80db55792a81nN62926EFA~.html"}, {"job": "Android", "company": "博彦科技", "salary": "14-19K", "link": "https://www.zhipin.com/job_detail/5370b3545e0885111XV63Nu0F1A~.html"}, {"job": "Android", "company": "易宝", "salary": "12-22K", "link": "https://www.zhipin.com/job_detail/cc5301f87cb9329e0HR73Ny9ElY~.html"}, {"job": "Android", "company": "OPPO", "salary": "10-20K", "link": "https://www.zhipin.com/job_detail/9928a819dbfd85c51XV73dW4F1A~.html"}, {"job": "Android", "company": "拓保软件", "salary": "11-22K", "link": "https://www.zhipin.com/job_detail/0feeb4e76e84848e0XF52dW1Fls~.html"}, {"job": "安卓Android高级开发工程师", "company": "中新云创", "salary": "15-23K·13薪", "link": "https://www.zhipin.com/job_detail/46f9ecd47fa53dae03Jz2Ni8E1U~.html"}, {"job": "Android", "company": "拓保软件", "salary": "11-20K", "link": "https://www.zhipin.com/job_detail/42a0883ad836c0ab0Xxz0ty7EFM~.html"}, {"job": "Android", "company": "法本", "salary": "12-24K·13薪", "link": "https://www.zhipin.com/job_detail/325448cbdf04428603N529i6FVE~.html"}, {"job": "Android", "company": "易宝软件", "salary": "12-20K", "link": "https://www.zhipin.com/job_detail/e20a3b32615a8d091nx82NW0FlE~.html"}, {"job": "Android", "company": "欧博思", "salary": "15-25K", "link": "https://www.zhipin.com/job_detail/263780d8a6d664961Hd-2dq9EVA~.html"}, {"job": "Android", "company": "OPPO", "salary": "10-15K", "link": "https://www.zhipin.com/job_detail/d509f7650fce26fb0Xx53tu7FlM~.html"}, {"job": "Android", "company": "联合创展", "salary": "20-30K·14薪", "link": "https://www.zhipin.com/job_detail/2f0b5ff00611df1d0X172ti-ElY~.html"}, {"job": "Android", "company": "博彦科技", "salary": "11-20K", "link": "https://www.zhipin.com/job_detail/21c6d17f397cad780Xx93Nq0EVE~.html"}, {"job": "Android", "company": "vivo", "salary": "25-50K", "link": "https://www.zhipin.com/job_detail/ec6e60eabfee40e51HJ529-1FVc~.html"}, {"job": "Android", "company": "OPPO", "salary": "15-30K", "link": "https://www.zhipin.com/job_detail/96af8804c08639b21XV70tm0FlQ~.html"}, {"job": "Android", "company": "OPPO", "salary": "15-30K", "link": "https://www.zhipin.com/job_detail/826e9654a887d8751XV52N--E1s~.html"}, {"job": "Android", "company": "广东欧珀", "salary": "20-40K", "link": "https://www.zhipin.com/job_detail/328120e5d37df9980XZ_2N60GFQ~.html"}, {"job": "Android", "company": "华为", "salary": "30-60K·24薪", "link": "https://www.zhipin.com/job_detail/245914732ba05d530Xx42d-7GFs~.html"}, {"job": "Android", "company": "鑫乐轩商贸有限公司", "salary": "25-50K", "link": "https://www.zhipin.com/job_detail/bff60af089bcf5b003d82N2_EFA~.html"}, {"job": "Android", "company": "国信", "salary": "15-25K", "link": "https://www.zhipin.com/job_detail/82c5f9896b5edd960nR93tS7Fw~~.html"}, {"job": "Android", "company": "腾讯音乐", "salary": "15-25K", "link": "https://www.zhipin.com/job_detail/89916cb93b69e5d61XF90tW_Elc~.html"}, {"job": "Android", "company": "OPPO", "salary": "15-30K", "link": "https://www.zhipin.com/job_detail/87e2464a6e9d58d4031y3Nu1EVQ~.html"}, {"job": "Android", "company": "OPPO广东移动...", "salary": "20-40K", "link": "https://www.zhipin.com/job_detail/59db0df5684bb03e1H1y29q0ElQ~.html"}, {"job": "Android", "company": "OPPO", "salary": "15-30K", "link": "https://www.zhipin.com/job_detail/90c073738b81e5ae1XJ_3ty-GFI~.html"}, {"job": "Android", "company": "OPPO", "salary": "20-30K", "link": "https://www.zhipin.com/job_detail/26f413cc4504f2181HZ62ty6EVE~.html"}, {"job": "Android", "company": "深圳市海思半导", "salary": "20-30K·15薪", "link": "https://www.zhipin.com/job_detail/5c14321018bcecb40HR52Nq8GFE~.html"}, {"job": "Android", "company": "百度", "salary": "20-40K", "link": "https://www.zhipin.com/job_detail/5960aefb17d795220X1z3du4GFI~.html"}, {"job": "Android", "company": "OPPO广东移动...", "salary": "15-30K", "link": "https://www.zhipin.com/job_detail/bd218165546c0bfa0Xxz3tq6FFI~.html"}, {"job": "Android", "company": "中软国际", "salary": "10-20K", "link": "https://www.zhipin.com/job_detail/fb095dfa711153920nd90ti0Fg~~.html"}, {"job": "Android", "company": "锐吉", "salary": "10-15K", "link": "https://www.zhipin.com/job_detail/899c742d34c9e92e1n140tW1EVY~.html"}, {"job": "Android", "company": "腾讯", "salary": "20-40K·14薪", "link": "https://www.zhipin.com/job_detail/06d34bb3f60f8fab0nF80t69GFU~.html"}, {"job": "Android", "company": "腾讯", "salary": "18-35K·14薪", "link": "https://www.zhipin.com/job_detail/adf58795802ad69c0nF80t64GVQ~.html"}, {"job": "Android", "company": "传音控股", "salary": "15-30K", "link": "https://www.zhipin.com/job_detail/0fb7cd8bec6aadfb03Z-3tq_FFs~.html"}, {"job": "Android", "company": "OPPO", "salary": "25-50K", "link": "https://www.zhipin.com/job_detail/af9209da63036e3203Vz2di1FFs~.html"}, {"job": "Android", "company": "广东欧珀", "salary": "15-30K", "link": "https://www.zhipin.com/job_detail/02eec2221ee049fb1HF40t-5FFM~.html"}, {"job": "Android", "company": "百度", "salary": "20-35K·15薪", "link": "https://www.zhipin.com/job_detail/355ca46c1645616d0XR80ty0EVA~.html"}, {"job": "Android", "company": "OPPO", "salary": "15-30K", "link": "https://www.zhipin.com/job_detail/2296ae984e1591a41H193tu_EVI~.html"}, {"job": "Android", "company": "OPPO", "salary": "26-50K", "link": "https://www.zhipin.com/job_detail/301a9528093d17611HB73ty6FVM~.html"}, {"job": "Android", "company": "OPPO", "salary": "20-35K", "link": "https://www.zhipin.com/job_detail/4e04a4691ff538431X142Nu9FlM~.html"}, {"job": "Android", "company": "OPPO", "salary": "25-50K", "link": "https://www.zhipin.com/job_detail/9bcb30496cc3b5181XZ829i5FVE~.html"}, {"job": "Android", "company": "华为", "salary": "40-80K", "link": "https://www.zhipin.com/job_detail/b608041fafecce4d1XZ43tu8GVU~.html"}, {"job": "Android", "company": "腾讯", "salary": "15-30K", "link": "https://www.zhipin.com/job_detail/04028cfacac6d7df1nx93tq7Els~.html"}, {"job": "Android", "company": "vivo", "salary": "20-40K", "link": "https://www.zhipin.com/job_detail/69952f84b77032321HJ529W8GVE~.html"}, {"job": "Android", "company": "OPPO", "salary": "15-30K", "link": "https://www.zhipin.com/job_detail/03857b1a6329c7a71XV53t2_FVo~.html"}, {"job": "Android", "company": "OPPO", "salary": "20-40K", "link": "https://www.zhipin.com/job_detail/38807819e9cad7091XF43dq9GVc~.html"}, {"job": "Android", "company": "广东欧珀", "salary": "30-35K", "link": "https://www.zhipin.com/job_detail/a5873501eba4adb90XN72tu1EVo~.html"}, {"job": "Android", "company": "百度深分", "salary": "15-30K·13薪", "link": "https://www.zhipin.com/job_detail/1b98b773db15d51f0nJ72di7F1Q~.html"}, {"job": "Android", "company": "腾讯", "salary": "18-35K·14薪", "link": "https://www.zhipin.com/job_detail/5b66eaafcba3e17d03Fy3t-5GVA~.html"}, {"job": "Android", "company": "君和睿通", "salary": "12-20K", "link": "https://www.zhipin.com/job_detail/d89e0ebaa73934b81nF43Nq1GFs~.html"}, {"job": "Android", "company": "特为科创信息技术", "salary": "13-19K", "link": "https://www.zhipin.com/job_detail/9b2f531ae552c9830HR62tq0GFQ~.html"}, {"job": "Android", "company": "全志科技", "salary": "12-24K·14薪", "link": "https://www.zhipin.com/job_detail/53a9883e68b0144e03x73t60EVY~.html"}, {"job": "Android", "company": "天势思维", "salary": "20-35K·13薪", "link": "https://www.zhipin.com/job_detail/98939ed0048b12f903B53N28Fls~.html"}, {"job": "Android", "company": "IDO", "salary": "10-20K", "link": "https://www.zhipin.com/job_detail/e0dfb870f03dc37e1nB93dq7F1o~.html"}, {"job": "Android", "company": "海贝壳科技", "salary": "9-13K", "link": "https://www.zhipin.com/job_detail/a4d9675f48fc3ebf1nJ_2dy-ElI~.html"}, {"job": "Android", "company": "深圳大牛造富源", "salary": "15-30K·13薪", "link": "https://www.zhipin.com/job_detail/ab643320406ea7f70X172d67FFE~.html"}, {"job": "Android", "company": "法本", "salary": "10-15K", "link": "https://www.zhipin.com/job_detail/8a71d98ca18badd50HR40t66FVA~.html"}, {"job": "android /ios开发工程师", "company": "文思海辉·金融", "salary": "12-18K", "link": "https://www.zhipin.com/job_detail/c1f29dd6cd47ac2c0ndz39-4FFI~.html"}, {"job": "Android", "company": "唯美神生物科技", "salary": "6-10K", "link": "https://www.zhipin.com/job_detail/7ba1d27ad31585460nV72tu8FVY~.html"}, {"job": "Android", "company": "百度", "salary": "18-25K", "link": "https://www.zhipin.com/job_detail/9a854bbca736a55f0nJ_39S5GFU~.html"}, {"job": "Android", "company": "微品致远", "salary": "14-20K", "link": "https://www.zhipin.com/job_detail/85605647271654740HR42Ni0FlE~.html"}, {"job": "Android", "company": "广东欧珀", "salary": "15-20K·16薪", "link": "https://www.zhipin.com/job_detail/f9efd89470ffee821H1_0t29Els~.html"}, {"job": "Android", "company": "顺丰科技", "salary": "25-35K", "link": "https://www.zhipin.com/job_detail/38e0d37ba7fc6d9b0nF639i7GVs~.html"}, {"job": "Android", "company": "OPPO", "salary": "15-20K·18薪", "link": "https://www.zhipin.com/job_detail/c49810b34512cd9d03R529q6FlM~.html"}, {"job": "Android", "company": "OPPO", "salary": "15-25K", "link": "https://www.zhipin.com/job_detail/f39e88127df506591X1y3dy-FFc~.html"}, {"job": "Android", "company": "乐信集团", "salary": "30-40K·16薪", "link": "https://www.zhipin.com/job_detail/e97659be3de82f9c0Xx_2t-4Elo~.html"}, {"job": "Android", "company": "新智联", "salary": "10-13K", "link": "https://www.zhipin.com/job_detail/96a4acb1d792cb140nN53t-6E1I~.html"}, {"job": "Android", "company": "腾讯音乐", "salary": "20-40K", "link": "https://www.zhipin.com/job_detail/23e859e4576ef1660Xd-092-EVA~.html"}, {"job": "Android", "company": "软通动力集团", "salary": "14-28K", "link": "https://www.zhipin.com/job_detail/eabb2a8bdaf7de9a1Xdz2Nu9GFc~.html"}, {"job": "Android", "company": "OPPO", "salary": "15-25K", "link": "https://www.zhipin.com/job_detail/504845070f7006e903V439-_EVY~.html"}, {"job": "Android", "company": "闻泰科技", "salary": "15-20K", "link": "https://www.zhipin.com/job_detail/49bb547e38f44b7c0XV43N2-F1Y~.html"}, {"job": "Android", "company": "中环智卫", "salary": "8-13K", "link": "https://www.zhipin.com/job_detail/84d745f12bf9743c1HJ72Nq-F1Y~.html"}, {"job": "Android", "company": "天阳科技", "salary": "9-14K", "link": "https://www.zhipin.com/job_detail/966432ced915d7c303d63NS9EVQ~.html"}, {"job": "Android", "company": "顺丰科技", "salary": "20-30K", "link": "https://www.zhipin.com/job_detail/b50bedab7d69ae880XBz2d64ElI~.html"}, {"job": "Android", "company": "顺丰科技", "salary": "20-40K·16薪", "link": "https://www.zhipin.com/job_detail/f5cee1e0342b7fe20nF639u8FlY~.html"}, {"job": "Android", "company": "广东欧珀", "salary": "20-21K", "link": "https://www.zhipin.com/job_detail/434981e367a607280nN62Ny4E1U~.html"}, {"job": "Android", "company": "顺丰科技", "salary": "25-35K", "link": "https://www.zhipin.com/job_detail/05e5e8ec87718a230n1-39m5GFU~.html"}, {"job": "Android", "company": "OPPO", "salary": "15-20K", "link": "https://www.zhipin.com/job_detail/7583dbd9a78a2c7203Jz3921FVI~.html"}, {"job": "Android", "company": "深圳市欢太科技有...", "salary": "25-50K", "link": "https://www.zhipin.com/job_detail/8b241d3c99e0caf50XJ-0tq7E1Y~.html"}, {"job": "Android", "company": "深圳市欢太科技有...", "salary": "20-40K", "link": "https://www.zhipin.com/job_detail/5a50b95edba8462a0XN929S9Flc~.html"}, {"job": "Android", "company": "顺丰科技", "salary": "25-35K", "link": "https://www.zhipin.com/job_detail/b55980000a296ef50n1-2dm6GVc~.html"}, {"job": "Android", "company": "OPPO", "salary": "15-16K", "link": "https://www.zhipin.com/job_detail/13d39053424cbeb203V42dq0EFA~.html"}, {"job": "Android", "company": "亿凯颠覆宇宙传媒", "salary": "12-20K", "link": "https://www.zhipin.com/job_detail/f5454d47abd8ed251Hd60ty9FFE~.html"}, {"job": "Android", "company": "上医实业", "salary": "14-20K", "link": "https://www.zhipin.com/job_detail/9c3bd58d89c3ecb31n152ti5FVE~.html"}, {"job": "Android", "company": "次元空间", "salary": "15-30K", "link": "https://www.zhipin.com/job_detail/cbd5282f59ec332c1HVy3961FVM~.html"}]